{
  "breakfast": [
    {
      "id": "b1",
      "name": "Idli + Sambaar",
      "ingredients": [
        "Rice",
        "Urad dal",
        "Salt"
      ]
    },
    {
      "id": "b2",
      "name": "Dosa + Onion Chutney",
      "ingredients": [
        "Rice",
        "Urad dal",
        "Salt",
        "Oil"
      ]
    },
    {
      "id": "b3",
      "name": "Poori + Paneer curry",
      "ingredients": [
        "Semolina",
        "Vegetables",
        "Oil",
        "Mustard seeds"
      ]
    },
    {
      "id": "mqdimrus37mnyz8befi",
      "name": "Puttu + Banana",
      "ingredients": []
    },
    {
      "id": "mqdiqs57aoxqnvx5qg",
      "name": "Appam + Kadala\\Paneer Curry",
      "ingredients": []
    }
  ],
  "lunch": [
    {
      "id": "l1",
      "name": "Aloo Paratha",
      "ingredients": [
        "Rice",
        "Toor dal",
        "Tomatoes",
        "Spices"
      ]
    },
    {
      "id": "l2",
      "name": "Poori + Paneer curry",
      "ingredients": [
        "Wheat flour",
        "Vegetables",
        "Spices",
        "Oil"
      ]
    },
    {
      "id": "l3",
      "name": "Chappathi + Paneer curry",
      "ingredients": [
        "Rice",
        "Mixed vegetables",
        "Spices",
        "Ghee"
      ]
    }
  ],
  "morningSnack": [
    {
      "id": "ms1",
      "name": "Fruits",
      "ingredients": [
        "Banana",
        "Apple",
        "Orange"
      ]
    },
    {
      "id": "ms2",
      "name": "Biscuits with Milk",
      "ingredients": [
        "Biscuits",
        "Milk"
      ]
    },
    {
      "id": "ms3",
      "name": "Banana Smoothie",
      "ingredients": [
        "Banana",
        "Milk",
        "Honey"
      ]
    },
    {
      "id": "mqdivfzoz9m1q3ezpkf",
      "name": "Dry Fruits Laddu",
      "ingredients": []
    },
    {
      "id": "mqdivqocnzj7yjd47cb",
      "name": "Aval",
      "ingredients": []
    }
  ],
  "eveningSnack": [
    {
      "id": "es1",
      "name": "Pakoda",
      "ingredients": [
        "Gram flour",
        "Onion",
        "Oil",
        "Spices"
      ]
    },
    {
      "id": "es2",
      "name": "Sandwich",
      "ingredients": [
        "Bread",
        "Vegetables",
        "Butter",
        "Cheese"
      ]
    },
    {
      "id": "es3",
      "name": "Samosa",
      "ingredients": [
        "All-purpose flour",
        "Potato",
        "Peas",
        "Spices",
        "Oil"
      ]
    }
  ]
}